behave2cucumberZephyr/__init__.py
behave2cucumberZephyr/__main__.py
tests/__init__.py
tests/test.py
behave2cucumberZephyr-0.0.1.dist-info/LICENSE
behave2cucumberZephyr-0.0.1.dist-info/METADATA
behave2cucumberZephyr-0.0.1.dist-info/WHEEL
behave2cucumberZephyr-0.0.1.dist-info/entry_points.txt
behave2cucumberZephyr-0.0.1.dist-info/top_level.txt
behave2cucumberZephyr-0.0.1.dist-info/RECORD
